servitorconnectqr/__init__.py
servitorconnectqr/cli.py
servitorconnectqr-1.0.2.dist-info/LICENSE
servitorconnectqr-1.0.2.dist-info/METADATA
servitorconnectqr-1.0.2.dist-info/WHEEL
servitorconnectqr-1.0.2.dist-info/entry_points.txt
servitorconnectqr-1.0.2.dist-info/top_level.txt
servitorconnectqr-1.0.2.dist-info/RECORD
