Metadata-Version: 2.1
Name: servitorconnectqr
Version: 1.0.2
Summary: A tool to use Universe Sourcecode with an intention to generate a QR Code.
Home-page: https://github.com/tsweet77/servitorconnectqr
Author: AnthroHeart (Thomas Sweet)
Author-email: healing@intentionrepeater.com
License: GPLv3
Classifier: Programming Language :: Python :: 3
Classifier: License :: OSI Approved :: GNU General Public License v3 (GPLv3)
Classifier: Operating System :: OS Independent
Requires-Python: >=3.6
License-File: LICENSE
